package_poo_semaine3/__init__.py
package_poo_semaine3/module1.py
package_poo_semaine3/module2.py
tests/__init__.py
tests/test_module1.py
package_poo_semaine3-0.1.0.dist-info/METADATA
package_poo_semaine3-0.1.0.dist-info/WHEEL
package_poo_semaine3-0.1.0.dist-info/top_level.txt
package_poo_semaine3-0.1.0.dist-info/RECORD
