Metadata-Version: 2.1
Name: package_poo_semaine3
Version: 0.1.0
Summary: exemple de package typique avec python
Home-page: https://github.com/username/mon_package
Author: courses
Author-email: courses@python.py
Classifier: Programming Language :: Python :: 3
Classifier: License :: OSI Approved :: MIT License
Classifier: Operating System :: OS Independent
Requires-Dist: numpy (>=1.18.0)
Requires-Dist: pandas (>=1.0.0)
